diffcraft/ai_client.py
diffcraft/cli.py
diffcraft/editor.py
diffcraft/gencraft_cli.py
diffcraft/generator.py
diffcraft/git_utils.py
diffcraft/main.py
diffcraft-2.1.5.dist-info/licenses/LICENSE
diffcraft-2.1.5.dist-info/METADATA
diffcraft-2.1.5.dist-info/WHEEL
diffcraft-2.1.5.dist-info/entry_points.txt
diffcraft-2.1.5.dist-info/top_level.txt
diffcraft-2.1.5.dist-info/RECORD
