Metadata-Version: 2.4
Name: DiffCraft
Version: 2.1.5
Summary: CLI co-pilot for Git and repository management.
Author-email: "Saurabh Baral (bvrvl)" <saurabh@bvrvl.com>
Classifier: Programming Language :: Python :: 3
Classifier: License :: OSI Approved :: MIT License
Classifier: Operating System :: OS Independent
Requires-Python: >=3.11
License-File: LICENSE
Requires-Dist: google-genai
Requires-Dist: python-dotenv
Requires-Dist: requests
Dynamic: license-file
